celery_farmer/__init__.py
celery_farmer/application.py
celery_farmer/broker.py
celery_farmer/cli.py
celery_farmer/enable_events.py
celery_farmer/event_listener.py
celery_farmer/queue_lengths.py
celery_farmer/statsd.py
celery_farmer/task.py
celery_farmer-0.2.2.dist-info/LICENSE
celery_farmer-0.2.2.dist-info/METADATA
celery_farmer-0.2.2.dist-info/WHEEL
celery_farmer-0.2.2.dist-info/entry_points.txt
celery_farmer-0.2.2.dist-info/top_level.txt
celery_farmer-0.2.2.dist-info/RECORD
