Metadata-Version: 2.1
Name: celery-farmer
Version: 0.2.2
Summary: Farmer will monitor how the Celery cluster is behaving
Home-page: https://github.com/woltapp/celery-farmer
Author: Wolt Enterprises Oy
Author-email: support@wolt.com
Classifier: Development Status :: 3 - Alpha
Classifier: License :: OSI Approved :: MIT License
Classifier: Operating System :: OS Independent
Classifier: Programming Language :: Python :: 3
Classifier: Programming Language :: Python :: 3.7
Classifier: Programming Language :: Python :: 3.8
Classifier: Programming Language :: Python :: 3.9
Classifier: Programming Language :: Python :: 3.10
Classifier: Programming Language :: Python :: Implementation :: CPython
License-File: LICENSE
Requires-Dist: statsd (<5.0,>=3.2.0)
Requires-Dist: redis (<5.0,>=2.10.0)
Requires-Dist: celery (<6.0,>=4.0)
Requires-Dist: click (<9.0,>=6.7)
